homogenize/__init__.py
homogenize/fast.py
homogenize/model.py
homogenize/running.py
homogenize/slow.py
homogenize-0.0.1.dist-info/METADATA
homogenize-0.0.1.dist-info/WHEEL
homogenize-0.0.1.dist-info/entry_points.txt
homogenize-0.0.1.dist-info/top_level.txt
homogenize-0.0.1.dist-info/RECORD
