Metadata-Version: 2.1
Name: homogenize
Version: 0.0.1
Summary: Survivial probability estimator for Regime Switching Orstein-Uhlenbeck triply stochastic process
Home-page: https://github.com/microprediction/homogenize
Author: microprediction
Author-email: info@microprediction.org
License: MIT
Platform: UNKNOWN
Classifier: License :: OSI Approved :: MIT License
Classifier: Programming Language :: Python :: 3
Classifier: Programming Language :: Python :: 3.7
Requires-Dist: numpy
Requires-Dist: requests
Requires-Dist: pathlib
